logical_operator/__init__.py
logical_operator/py.typed
logical_operator-1.0.0.dist-info/LICENSE
logical_operator-1.0.0.dist-info/METADATA
logical_operator-1.0.0.dist-info/WHEEL
logical_operator-1.0.0.dist-info/top_level.txt
logical_operator-1.0.0.dist-info/RECORD
