Metadata-Version: 2.1
Name: logical-operator
Version: 1.0.0
Summary: Normalized logical operators as functions.
Author: Braedyn L
License: MIT License
Project-URL: Homepage, https://github.com/braedynl/logical_operator
Project-URL: Source, https://github.com/braedynl/logical_operator
Project-URL: Documentation, https://github.com/braedynl/logical_operator
Project-URL: Bug Tracker, https://github.com/braedynl/logical_operator/issues
Keywords: logical,operator,functions
Classifier: Programming Language :: Python :: 3
Classifier: Programming Language :: Python :: 3.8
Classifier: Programming Language :: Python :: 3.9
Classifier: Programming Language :: Python :: 3.10
Classifier: Programming Language :: Python :: 3.11
Classifier: License :: OSI Approved :: MIT License
Classifier: Operating System :: OS Independent
Classifier: Topic :: Software Development :: Libraries :: Python Modules
Requires-Python: >=3.8
License-File: LICENSE
